ritual_arweave/__init__.py
ritual_arweave/__main__.py
ritual_arweave/cli.py
ritual_arweave/concurrency_utils.py
ritual_arweave/file_manager.py
ritual_arweave/py.typed
ritual_arweave/repo_manager.py
ritual_arweave/types.py
ritual_arweave/utils.py
ritual_arweave/version.py
ritual_arweave-0.2.0.dist-info/METADATA
ritual_arweave-0.2.0.dist-info/WHEEL
ritual_arweave-0.2.0.dist-info/entry_points.txt
ritual_arweave-0.2.0.dist-info/RECORD
