Metadata-Version: 2.3
Name: ritual-arweave
Version: 0.2.0
Summary: Ritual Arweave library
Author-email: ritual <hello@ritual.net>
Requires-Python: >=3.9
Requires-Dist: aiohttp<4.0.0,>=3.10.5
Requires-Dist: click<9.0.0,>=8.1.7
Requires-Dist: nicelog<1.0.0,>=0.1.0
Requires-Dist: pydantic<3.0.0,>=2.5.3
Requires-Dist: python-dotenv<2.0.0,>=1.0.0
Requires-Dist: reretry<1.0.0,>=0.11.8
Requires-Dist: rich<14.0.0,>=13.7.1
Requires-Dist: ritual-pyarweave<0.2.0,>=0.1.0.3
Requires-Dist: tqdm<5.0.0,>=4.65.1
Requires-Dist: web3<7.0.0,>=6.19.0
Provides-Extra: development
Requires-Dist: isort<6.0.0,>=5.13.2; extra == 'development'
Requires-Dist: mypy<2.0.0,>=1.9.0; extra == 'development'
Requires-Dist: pre-commit<4.0.0,>=3.7.0; extra == 'development'
Requires-Dist: pytest<9.0.0,>=8.1.1; extra == 'development'
Requires-Dist: ruff<1.0.0,>=0.3.5; extra == 'development'
Requires-Dist: types-requests<3.0,>=2.31.0.20240406; extra == 'development'
Requires-Dist: types-retry<1.0,>=0.9.9.4; extra == 'development'
Requires-Dist: types-tqdm<5.0,>=4.66.0.20240106; extra == 'development'
